manoc/__init__.py
manoc/cli.py
manoc/commands/__init__.py
manoc/commands/cmd_env.py
manoc/commands/cmd_login.py
manoc/commands/cmd_logout.py
manoc/commands/cmd_operation-get.py
manoc/commands/cmd_operation-list.py
manoc/commands/cmd_operation-retry.py
manoc/commands/cmd_package-delete.py
manoc/commands/cmd_package-get.py
manoc/commands/cmd_package-list.py
manoc/commands/cmd_package-onboard.py
manoc/commands/cmd_prerequisite-execution-get.py
manoc/commands/cmd_prerequisite-execution-list.py
manoc/commands/cmd_prerequisite-workflow-delete.py
manoc/commands/cmd_prerequisite-workflow-get.py
manoc/commands/cmd_prerequisite-workflow-list.py
manoc/commands/cmd_prerequisite-workflow-run.py
manoc/commands/cmd_prerequisite-workflow-upload.py
manoc/commands/cmd_register.py
manoc/commands/cmd_vnf-create.py
manoc/commands/cmd_vnf-delete.py
manoc/commands/cmd_vnf-get.py
manoc/commands/cmd_vnf-heal.py
manoc/commands/cmd_vnf-instantiate.py
manoc/commands/cmd_vnf-list.py
manoc/commands/cmd_vnf-scale.py
manoc/commands/cmd_vnf-terminate.py
manoc/utils/__init__.py
manoc/utils/auth.py
manoc/utils/common.py
manoc/utils/config.py
manoc/utils/context.py
manoc/utils/logging.py
manoc-1.2.6.dist-info/METADATA
manoc-1.2.6.dist-info/RECORD
manoc-1.2.6.dist-info/WHEEL
manoc-1.2.6.dist-info/entry_points.txt
manoc-1.2.6.dist-info/top_level.txt
