Metadata-Version: 2.1
Name: manoc
Version: 1.2.6
Summary: UNKNOWN
Home-page: UNKNOWN
Author: UNKNOWN
Author-email: UNKNOWN
License: UNKNOWN
Platform: UNKNOWN
Requires-Dist: click
Requires-Dist: configparser
Requires-Dist: requests
Requires-Dist: prettytable
Requires-Dist: jmespath
